django_dynamic_theme/__init__.py
django_dynamic_theme/admin.py
django_dynamic_theme/apps.py
django_dynamic_theme/context_processor.py
django_dynamic_theme/errors.py
django_dynamic_theme/middleware.py
django_dynamic_theme/migrations/0001_initial.py
django_dynamic_theme/migrations/0002_background_name.py
django_dynamic_theme/migrations/0003_alter_background_primary_bg.py
django_dynamic_theme/migrations/0004_alter_background_primary_bg_theme.py
django_dynamic_theme/migrations/0005_remove_theme_background_theme_background.py
django_dynamic_theme/migrations/0006_alter_theme_background.py
django_dynamic_theme/migrations/0007_theme_default_theme_only_one_theme_can_be_default_.py
django_dynamic_theme/migrations/0008_alter_theme_default.py
django_dynamic_theme/migrations/0009_navbar.py
django_dynamic_theme/migrations/0010_theme_navbar.py
django_dynamic_theme/migrations/0011_navbar_font_size.py
django_dynamic_theme/migrations/0012_navbar_text_color.py
django_dynamic_theme/migrations/0013_navbar_text_opacity.py
django_dynamic_theme/migrations/0014_alter_navbar_opacity.py
django_dynamic_theme/migrations/0015_mediagallery.py
django_dynamic_theme/migrations/0016_theme_media_gallery.py
django_dynamic_theme/migrations/0017_alter_mediagallery_options_alter_theme_navbar.py
django_dynamic_theme/migrations/__init__.py
django_dynamic_theme/models.py
django_dynamic_theme/signals.py
django_dynamic_theme/util/__init__.py
django_dynamic_theme/util/color_converter.py
django_dynamic_theme/util/scss_editor.py
django_dynamic_theme-0.0.10.dist-info/LICENSE
django_dynamic_theme-0.0.10.dist-info/METADATA
django_dynamic_theme-0.0.10.dist-info/WHEEL
django_dynamic_theme-0.0.10.dist-info/RECORD
