Metadata-Version: 2.1
Name: django-dynamic-theme
Version: 0.0.10
Summary: This enables the administrator of a django website to change the theme on the fly.
Author: Segelzwerg
Author-email: 25705862+Segelzwerg@users.noreply.github.com
Requires-Python: >=3.10,<4.0
Classifier: Framework :: Django
Classifier: Framework :: Django :: 4.2
Classifier: Framework :: Django :: 5.0
Classifier: Intended Audience :: Developers
Classifier: Natural Language :: English
Classifier: Operating System :: OS Independent
Classifier: Programming Language :: Python :: 3
Classifier: Programming Language :: Python :: 3.10
Classifier: Programming Language :: Python :: 3.11
Classifier: Programming Language :: Python :: 3.12
Requires-Dist: django (>=5.0,<6.0)
Requires-Dist: django-colorfield (>=0.11.0,<0.12.0)
Requires-Dist: django-compressor (>=4.4,<5.0)
Requires-Dist: django-libsass (>=0.9,<0.10)
